{
  "city": "bangkok",
  "batch": 6,
  "spots": [
    {
      "name": {
        "en": "Klong Lat Mayom Floating Market",
        "th": "ตลาดน้ำคลองลัดมะยม"
      },
      "description": {
        "en": "Authentic floating market for locals. Weekend only, less touristy than others.",
        "th": "ตลาดน้ำแท้สำหรับคนท้องถิ่น เฉพาะสุดสัปดาห์ นักท่องเที่ยวน้อยกว่าที่อื่น"
      },
      "address": {
        "en": "Klong Lat Mayom, Taling Chan, Bangkok",
        "th": "คลองลัดมะยม ตลิ่งชัน กรุงเทพฯ"
      },
      "category": "Market",
      "subcategories": [
        "Floating Market",
        "Weekend",
        "Local"
      ],
      "localley_score": 5,
      "local_percentage": 85,
      "best_time": "Weekend morning",
      "tips": [
        "Weekend only",
        "Local market",
        "Boat noodles"
      ],
      "neighborhood": "Taling Chan",
      "photos": [],
      "verified": false,
      "trending_score": 0.72,
      "best_times": {
        "en": "Weekend morning"
      },
      "latitude": 13.7608,
      "longitude": 100.4156
    },
    {
      "name": {
        "en": "Taling Chan Floating Market",
        "th": "ตลาดน้ำตลิ่งชัน"
      },
      "description": {
        "en": "Smaller floating market near Bangkok. Boat vendors and riverside dining.",
        "th": "ตลาดน้ำเล็กๆ ใกล้กรุงเทพฯ พ่อค้าเรือและอาหารริมแม่น้ำ"
      },
      "address": {
        "en": "Taling Chan, Bangkok",
        "th": "ตลิ่งชัน กรุงเทพฯ"
      },
      "category": "Market",
      "subcategories": [
        "Floating Market",
        "Riverside",
        "Food"
      ],
      "localley_score": 5,
      "local_percentage": 80,
      "best_time": "Weekend morning",
      "tips": [
        "Weekend only",
        "Smaller than others",
        "Easy access"
      ],
      "neighborhood": "Taling Chan",
      "photos": [],
      "verified": false,
      "trending_score": 0.59,
      "best_times": {
        "en": "Weekend morning"
      },
      "latitude": 13.7764,
      "longitude": 100.4566
    },
    {
      "name": {
        "en": "Amphawa Floating Market",
        "th": "ตลาดน้ำอัมพวา"
      },
      "description": {
        "en": "Popular floating market 90 minutes from Bangkok. Evening firefly tours.",
        "th": "ตลาดน้ำยอดนิยม 90 นาทีจากกรุงเทพฯ ทัวร์หิ่งห้อยตอนเย็น"
      },
      "address": {
        "en": "Amphawa, Samut Songkhram",
        "th": "อัมพวา สมุทรสงคราม"
      },
      "category": "Market",
      "subcategories": [
        "Floating Market",
        "Day Trip",
        "Fireflies"
      ],
      "localley_score": 4,
      "local_percentage": 60,
      "best_time": "Weekend evening",
      "tips": [
        "Day trip",
        "Firefly tours",
        "Weekend best"
      ],
      "neighborhood": "Day Trip",
      "photos": [],
      "verified": false,
      "trending_score": 0.45,
      "best_times": {
        "en": "Weekend evening"
      }
    },
    {
      "name": {
        "en": "Damnoen Saduak Floating Market",
        "th": "ตลาดน้ำดำเนินสะดวก"
      },
      "description": {
        "en": "Most famous floating market, very touristy. Classic Thai photo opportunity.",
        "th": "ตลาดน้ำที่โด่งดังที่สุด นักท่องเที่ยวมาก โอกาสถ่ายรูปไทยคลาสสิก"
      },
      "address": {
        "en": "Damnoen Saduak, Ratchaburi",
        "th": "ดำเนินสะดวก ราชบุรี"
      },
      "category": "Market",
      "subcategories": [
        "Floating Market",
        "Tourist",
        "Classic"
      ],
      "localley_score": 2,
      "local_percentage": 20,
      "best_time": "Early morning",
      "tips": [
        "Very touristy",
        "Go early",
        "Negotiate prices"
      ],
      "neighborhood": "Day Trip",
      "photos": [],
      "verified": false,
      "trending_score": 0.16,
      "best_times": {
        "en": "Early morning"
      }
    },
    {
      "name": {
        "en": "Maeklong Railway Market",
        "th": "ตลาดร่มหุบ แม่กลอง"
      },
      "description": {
        "en": "Market on active railway tracks. Vendors pull back awnings for passing trains.",
        "th": "ตลาดบนรางรถไฟที่ใช้งาน พ่อค้าดึงร่มถอยเมื่อรถไฟผ่าน"
      },
      "address": {
        "en": "Maeklong, Samut Songkhram",
        "th": "แม่กลอง สมุทรสงคราม"
      },
      "category": "Market",
      "subcategories": [
        "Railway",
        "Unique",
        "Day Trip"
      ],
      "localley_score": 3,
      "local_percentage": 40,
      "best_time": "Train times",
      "tips": [
        "Check train schedule",
        "Unique experience",
        "Day trip from Bangkok"
      ],
      "neighborhood": "Day Trip",
      "photos": [],
      "verified": false,
      "trending_score": 0.26,
      "best_times": {
        "en": "Train times"
      }
    },
    {
      "name": {
        "en": "Bang Nam Pheung Floating Market",
        "th": "ตลาดน้ำบางน้ำผึ้ง"
      },
      "description": {
        "en": "Small local floating market in Bang Krachao. Part of green lung experience.",
        "th": "ตลาดน้ำท้องถิ่นเล็กๆ ในบางกระเจ้า ส่วนหนึ่งของประสบการณ์ปอดกรุงเทพฯ"
      },
      "address": {
        "en": "Bang Nam Pheung, Phra Pradaeng, Samut Prakan",
        "th": "บางน้ำผึ้ง พระประแดง สมุทรปราการ"
      },
      "category": "Market",
      "subcategories": [
        "Floating Market",
        "Local",
        "Nature"
      ],
      "localley_score": 5,
      "local_percentage": 90,
      "best_time": "Weekend morning",
      "tips": [
        "Near Bang Krachao",
        "Very local",
        "Weekend only"
      ],
      "neighborhood": "Bang Krachao",
      "photos": [],
      "verified": false,
      "trending_score": 0.58,
      "best_times": {
        "en": "Weekend morning"
      },
      "latitude": 13.6801,
      "longitude": 100.5743
    },
    {
      "name": {
        "en": "Bang Krachao Green Lung",
        "th": "บางกระเจ้า"
      },
      "description": {
        "en": "Bangkok's 'green lung' cycling paradise. Urban jungle with bike paths.",
        "th": "สวรรค์ปั่นจักรยาน 'ปอดกรุงเทพฯ' ป่าในเมืองมีทางจักรยาน"
      },
      "address": {
        "en": "Bang Krachao, Phra Pradaeng, Samut Prakan",
        "th": "บางกระเจ้า พระประแดง สมุทรปราการ"
      },
      "category": "Outdoor",
      "subcategories": [
        "Cycling",
        "Nature",
        "Green"
      ],
      "localley_score": 5,
      "local_percentage": 80,
      "best_time": "Morning",
      "tips": [
        "Rent bikes there",
        "Ferry crossing",
        "Escape the city"
      ],
      "neighborhood": "Bang Krachao",
      "latitude": 13.700069099999999,
      "longitude": 100.54910830000001,
      "photos": [],
      "verified": false,
      "trending_score": 0.67,
      "best_times": {
        "en": "Morning"
      }
    },
    {
      "name": {
        "en": "Sri Nakhon Khuean Khan Park",
        "th": "สวนศรีนครเขื่อนขันธ์"
      },
      "description": {
        "en": "Large park in Bang Krachao. Nature trails and botanical garden.",
        "th": "สวนใหญ่ในบางกระเจ้า เส้นทางธรรมชาติและสวนพฤกษศาสตร์"
      },
      "address": {
        "en": "73 Soi Wat Rat Rangsan, Tambon Bang Kachao, Amphoe Phra Pradaeng, Chang Wat Samut Prakan 10130, Thailand",
        "th": "สวนศรีนครฯ บางกระเจ้า"
      },
      "category": "Outdoor",
      "subcategories": [
        "Park",
        "Nature",
        "Botanical"
      ],
      "localley_score": 5,
      "local_percentage": 90,
      "best_time": "Morning",
      "tips": [
        "In Bang Krachao",
        "Nature escape",
        "Bike access"
      ],
      "neighborhood": "Bang Krachao",
      "latitude": 13.6968366,
      "longitude": 100.5649237,
      "photos": [],
      "verified": false,
      "trending_score": 0.66,
      "best_times": {
        "en": "Morning"
      }
    },
    {
      "name": {
        "en": "Rot Fai Park",
        "th": "สวนรถไฟ"
      },
      "description": {
        "en": "Large park near Chatuchak for exercise. Former railway yard turned public space.",
        "th": "สวนใหญ่ใกล้จตุจักรสำหรับออกกำลังกาย อดีตลานรถไฟกลายเป็นพื้นที่สาธารณะ"
      },
      "address": {
        "en": "Rot Fai Park, Chatuchak, Bangkok",
        "th": "สวนรถไฟ จตุจักร กรุงเทพฯ"
      },
      "category": "Outdoor",
      "subcategories": [
        "Park",
        "Exercise",
        "Running"
      ],
      "localley_score": 5,
      "local_percentage": 90,
      "best_time": "Early morning/Evening",
      "tips": [
        "Running track",
        "Near Chatuchak",
        "Exercise haven"
      ],
      "neighborhood": "Chatuchak",
      "photos": [],
      "verified": false,
      "trending_score": 0.69,
      "best_times": {
        "en": "Early morning/Evening"
      },
      "latitude": 13.8118,
      "longitude": 100.5537
    },
    {
      "name": {
        "en": "Wachirabenchathat Park",
        "th": "สวนวชิรเบญจทัศ"
      },
      "description": {
        "en": "Large connected park near Chatuchak. Lakes, paths, and family activities.",
        "th": "สวนเชื่อมต่อใหญ่ใกล้จตุจักร ทะเลสาบ ทางเดิน และกิจกรรมครอบครัว"
      },
      "address": {
        "en": "Wachirabenchathat Park, Chatuchak, Bangkok",
        "th": "สวนวชิรฯ จตุจักร กรุงเทพฯ"
      },
      "category": "Outdoor",
      "subcategories": [
        "Park",
        "Lakes",
        "Family"
      ],
      "localley_score": 5,
      "local_percentage": 90,
      "best_time": "Morning/Evening",
      "tips": [
        "Connected to Rot Fai",
        "Paddle boats",
        "Large area"
      ],
      "neighborhood": "Chatuchak",
      "photos": [],
      "verified": false,
      "trending_score": 0.71,
      "best_times": {
        "en": "Morning/Evening"
      },
      "latitude": 13.8118,
      "longitude": 100.5537
    },
    {
      "name": {
        "en": "Ramkhamhaeng Night Market",
        "th": "ตลาดกลางคืนรามคำแหง"
      },
      "description": {
        "en": "Local night market near university. Student prices and authentic food.",
        "th": "ตลาดกลางคืนท้องถิ่นใกล้มหาวิทยาลัย ราคานักศึกษาและอาหารแท้"
      },
      "address": {
        "en": "Ramkhamhaeng, Bangkok",
        "th": "รามคำแหง กรุงเทพฯ"
      },
      "category": "Market",
      "subcategories": [
        "Night Market",
        "Student",
        "Local"
      ],
      "localley_score": 6,
      "local_percentage": 95,
      "best_time": "Evening",
      "tips": [
        "Very local",
        "Student prices",
        "University area"
      ],
      "neighborhood": "Ramkhamhaeng",
      "photos": [],
      "verified": false,
      "trending_score": 0.37,
      "best_times": {
        "en": "Evening"
      },
      "latitude": 13.743,
      "longitude": 100.5997
    },
    {
      "name": {
        "en": "Huai Khwang Night Market",
        "th": "ตลาดกลางคืนห้วยขวาง"
      },
      "description": {
        "en": "24-hour street food and night market. Thai-Chinese community.",
        "th": "สตรีทฟู้ดและตลาดกลางคืน 24 ชั่วโมง ชุมชนไทย-จีน"
      },
      "address": {
        "en": "Huai Khwang, Bangkok",
        "th": "ห้วยขวาง กรุงเทพฯ"
      },
      "category": "Food",
      "subcategories": [
        "24-hour",
        "Street Food",
        "Chinese-Thai"
      ],
      "localley_score": 5,
      "local_percentage": 90,
      "best_time": "Late night",
      "tips": [
        "24-hour food",
        "Thai-Chinese area",
        "Very local"
      ],
      "neighborhood": "Huai Khwang",
      "photos": [],
      "verified": false,
      "trending_score": 0.66,
      "best_times": {
        "en": "Late night"
      },
      "latitude": 13.7786,
      "longitude": 100.5746
    },
    {
      "name": {
        "en": "Ratchada Temple Fair",
        "th": "งานวัดรัชดา"
      },
      "description": {
        "en": "Traditional temple fair atmosphere. Carnival rides and local food.",
        "th": "บรรยากาศงานวัดดั้งเดิม เครื่องเล่นและอาหารท้องถิ่น"
      },
      "address": {
        "en": "Ratchada, Bangkok",
        "th": "รัชดา กรุงเทพฯ"
      },
      "category": "Entertainment",
      "subcategories": [
        "Temple Fair",
        "Carnival",
        "Local"
      ],
      "localley_score": 5,
      "local_percentage": 90,
      "best_time": "Evening",
      "tips": [
        "Traditional fair",
        "Carnival rides",
        "Thai experience"
      ],
      "neighborhood": "Ratchada",
      "photos": [],
      "verified": false,
      "trending_score": 0.68,
      "best_times": {
        "en": "Evening"
      },
      "latitude": 13.7282,
      "longitude": 100.5249
    },
    {
      "name": {
        "en": "The Street Ratchada",
        "th": "เดอะสตรีท รัชดา"
      },
      "description": {
        "en": "Shopping and entertainment complex. Movies, shopping, and dining.",
        "th": "ศูนย์ช้อปปิ้งและบันเทิง หนัง ช้อปปิ้ง และอาหาร"
      },
      "address": {
        "en": "The Street, Ratchada, Bangkok",
        "th": "เดอะสตรีท รัชดา กรุงเทพฯ"
      },
      "category": "Shopping",
      "subcategories": [
        "Mall",
        "Entertainment",
        "Movies"
      ],
      "localley_score": 4,
      "local_percentage": 75,
      "best_time": "Evening",
      "tips": [
        "Near night market",
        "Cinema",
        "Local mall"
      ],
      "neighborhood": "Ratchada",
      "photos": [],
      "verified": false,
      "trending_score": 0.51,
      "best_times": {
        "en": "Evening"
      },
      "latitude": 13.7701,
      "longitude": 100.5721
    },
    {
      "name": {
        "en": "Esplanade Ratchada",
        "th": "เอสพละนาด รัชดา"
      },
      "description": {
        "en": "Entertainment mall near MRT. Multiple cinemas and bowling.",
        "th": "ห้างบันเทิงใกล้รถไฟฟ้า โรงหนังหลายโรงและโบว์ลิ่ง"
      },
      "address": {
        "en": "Esplanade, Ratchada, Bangkok",
        "th": "เอสพละนาด รัชดา กรุงเทพฯ"
      },
      "category": "Entertainment",
      "subcategories": [
        "Mall",
        "Cinema",
        "Bowling"
      ],
      "localley_score": 4,
      "local_percentage": 80,
      "best_time": "Evening",
      "tips": [
        "Near MRT",
        "Multiple cinemas",
        "Entertainment focus"
      ],
      "neighborhood": "Ratchada",
      "photos": [],
      "verified": false,
      "trending_score": 0.51,
      "best_times": {
        "en": "Evening"
      }
    },
    {
      "name": {
        "en": "Phahurat Little India",
        "th": "พาหุรัด"
      },
      "description": {
        "en": "Bangkok's Little India near Chinatown. Fabric market and Indian food.",
        "th": "ลิตเติ้ลอินเดียกรุงเทพฯ ใกล้ไชน่าทาวน์ ตลาดผ้าและอาหารอินเดีย"
      },
      "address": {
        "en": "Phahurat, Phra Nakhon, Bangkok",
        "th": "พาหุรัด เขตพระนคร กรุงเทพฯ"
      },
      "category": "Shopping",
      "subcategories": [
        "Indian",
        "Fabric",
        "Ethnic"
      ],
      "localley_score": 5,
      "local_percentage": 80,
      "best_time": "Morning",
      "tips": [
        "Fabric shopping",
        "Indian restaurants",
        "Near Chinatown"
      ],
      "neighborhood": "Phahurat",
      "photos": [],
      "verified": false,
      "trending_score": 0.72,
      "best_times": {
        "en": "Morning"
      },
      "latitude": 13.7447,
      "longitude": 100.5002
    },
    {
      "name": {
        "en": "Pak Khlong Flower Market",
        "th": "ปากคลองตลาด"
      },
      "description": {
        "en": "Wholesale flower market active at night. Best visited pre-dawn.",
        "th": "ตลาดดอกไม้ขายส่งคึกคักตอนกลางคืน ไปก่อนรุ่งสางดีที่สุด"
      },
      "address": {
        "en": "Pak Khlong Talat, Phra Nakhon, Bangkok",
        "th": "ปากคลองตลาด เขตพระนคร กรุงเทพฯ"
      },
      "category": "Market",
      "subcategories": [
        "Flowers",
        "Night",
        "Wholesale"
      ],
      "localley_score": 5,
      "local_percentage": 85,
      "best_time": "2-5am",
      "tips": [
        "Pre-dawn best",
        "Wholesale prices",
        "Photo opportunity"
      ],
      "neighborhood": "Old Town",
      "photos": [],
      "verified": false,
      "trending_score": 0.67,
      "best_times": {
        "en": "2-5am"
      },
      "latitude": 13.7417,
      "longitude": 100.4963
    },
    {
      "name": {
        "en": "Chao Phraya Dinner Cruise",
        "th": "ล่องเรือเจ้าพระยา"
      },
      "description": {
        "en": "Evening river cruise with dinner. Views of illuminated temples.",
        "th": "ล่องเรือแม่น้ำยามเย็นพร้อมอาหาร วิววัดส่องสว่าง"
      },
      "address": {
        "en": "Chao Phraya River, Bangkok",
        "th": "แม่น้ำเจ้าพระยา กรุงเทพฯ"
      },
      "category": "Entertainment",
      "subcategories": [
        "Cruise",
        "Dinner",
        "River"
      ],
      "localley_score": 2,
      "local_percentage": 25,
      "best_time": "Evening",
      "tips": [
        "Multiple companies",
        "Temple views",
        "Book ahead"
      ],
      "neighborhood": "River",
      "photos": [],
      "verified": false,
      "trending_score": 0.19,
      "best_times": {
        "en": "Evening"
      },
      "latitude": 13.7503,
      "longitude": 100.4875
    },
    {
      "name": {
        "en": "Chao Phraya Express Boat",
        "th": "เรือด่วนเจ้าพระยา"
      },
      "description": {
        "en": "Public river transport boat. Cheap way to see riverside Bangkok.",
        "th": "เรือขนส่งสาธารณะทางแม่น้ำ วิธีถูกๆ ดูกรุงเทพฯ ริมแม่น้ำ"
      },
      "address": {
        "en": "Various Piers, Chao Phraya River",
        "th": "ท่าเรือต่างๆ แม่น้ำเจ้าพระยา"
      },
      "category": "Entertainment",
      "subcategories": [
        "Transport",
        "Boat",
        "Cheap"
      ],
      "localley_score": 4,
      "local_percentage": 70,
      "best_time": "Daytime",
      "tips": [
        "Flag color = route",
        "Very cheap",
        "Rush hour packed"
      ],
      "neighborhood": "River",
      "photos": [],
      "verified": false,
      "trending_score": 0.48,
      "best_times": {
        "en": "Daytime"
      }
    },
    {
      "name": {
        "en": "Khlong Saen Saep Canal Boat",
        "th": "เรือคลองแสนแสบ"
      },
      "description": {
        "en": "Fast canal boat through central Bangkok. Local commuter experience.",
        "th": "เรือคลองเร็วผ่านใจกลางกรุงเทพฯ ประสบการณ์ผู้โดยสารท้องถิ่น"
      },
      "address": {
        "en": "Khlong Saen Saep, Bangkok",
        "th": "คลองแสนแสบ กรุงเทพฯ"
      },
      "category": "Entertainment",
      "subcategories": [
        "Transport",
        "Canal",
        "Local"
      ],
      "localley_score": 5,
      "local_percentage": 90,
      "best_time": "Rush hour",
      "tips": [
        "Very fast",
        "Splash guard needed",
        "Local experience"
      ],
      "neighborhood": "Various",
      "photos": [],
      "verified": false,
      "trending_score": 0.59,
      "best_times": {
        "en": "Rush hour"
      }
    }
  ]
}